{
  "version": "6.1.3",
  "flags": {},
  "shapes": [
    {
      "label": "parking",
      "points": [
        [
          371.9480519480519,
          349.87012987012986
        ],
        [
          640.0,
          512.9506856779584
        ],
        [
          640.0,
          436.23376623376623
        ],
        [
          408.961038961039,
          351.16883116883116
        ]
      ],
      "group_id": null,
      "description": "",
      "shape_type": "polygon",
      "flags": {},
      "mask": null
    },
    {
      "label": "roadway",
      "points": [
        [
          315.4545454545455,
          320.64935064935065
        ],
        [
          0.0,
          433.5356691022695
        ],
        [
          0.0,
          634.2857142857142
        ],
        [
          640.0,
          634.9342752909838
        ],
        [
          639.4805194805194,
          517.4025974025974
        ],
        [
          327.1428571428571,
          324.5454545454545
        ]
      ],
      "group_id": null,
      "description": "",
      "shape_type": "polygon",
      "flags": {},
      "mask": null
    },
    {
      "label": "sidewalk",
      "points": [
        [
          245.97402597402598,
          342.07792207792204
        ],
        [
          0.0,
          423.01539077888685
        ],
        [
          0.0,
          343.37662337662334
        ],
        [
          166.10389610389612,
          338.1818181818182
        ]
      ],
      "group_id": null,
      "description": "",
      "shape_type": "polygon",
      "flags": {},
      "mask": null
    },
    {
      "label": "sidewalk",
      "points": [
        [
          381.038961038961,
          342.07792207792204
        ],
        [
          370.0,
          345.3246753246753
        ],
        [
          373.8961038961039,
          349.2207792207792
        ],
        [
          411.5584415584415,
          349.87012987012986
        ],
        [
          640.0,
          432.8304853041695
        ],
        [
          640.0,
          388.83116883116884
        ],
        [
          432.9870129870129,
          342.7272727272727
        ]
      ],
      "group_id": null,
      "description": "",
      "shape_type": "polygon",
      "flags": {},
      "mask": null
    },
    {
      "label": "sidewalk",
      "points": [
        [
          347.92207792207785,
          326.49350649350646
        ],
        [
          377.1428571428571,
          333.6363636363636
        ],
        [
          443.37662337662334,
          331.038961038961
        ],
        [
          442.72727272727263,
          336.8831168831169
        ],
        [
          373.8961038961039,
          338.1818181818182
        ]
      ],
      "group_id": null,
      "description": "",
      "shape_type": "polygon",
      "flags": {},
      "mask": null
    }
  ],
  "imagePath": "115-1.png",
  "imageData": null,
  "imageHeight": 640,
  "imageWidth": 640
}