{
  "version": "6.1.3",
  "flags": {},
  "shapes": [
    {
      "label": "parking",
      "points": [
        [
          303.11688311688306,
          327.79220779220776
        ],
        [
          0.0,
          510.52662205411696
        ],
        [
          0.0,
          440.77922077922074
        ],
        [
          288.18181818181813,
          327.1428571428571
        ]
      ],
      "group_id": null,
      "description": "",
      "shape_type": "polygon",
      "flags": {},
      "mask": null
    },
    {
      "label": "roadway",
      "points": [
        [
          309.6103896103896,
          320.0
        ],
        [
          0.0,
          507.91709204871904
        ],
        [
          0.0,
          638.1818181818181
        ],
        [
          640.0,
          638.1818181818181
        ],
        [
          640.0,
          431.038961038961
        ],
        [
          328.4415584415584,
          320.0
        ]
      ],
      "group_id": null,
      "description": "",
      "shape_type": "polygon",
      "flags": {},
      "mask": null
    },
    {
      "label": "sidewalk",
      "points": [
        [
          334.2857142857142,
          322.5974025974026
        ],
        [
          640.0,
          426.60921784981934
        ],
        [
          640.0,
          344.025974025974
        ],
        [
          357.6623376623377,
          318.7012987012987
        ]
      ],
      "group_id": null,
      "description": "",
      "shape_type": "polygon",
      "flags": {},
      "mask": null
    },
    {
      "label": "sidewalk",
      "points": [
        [
          287.53246753246754,
          325.19480519480516
        ],
        [
          -5.684341886080802e-14,
          432.2606376349179
        ],
        [
          0.0,
          386.8831168831169
        ],
        [
          258.961038961039,
          325.8441558441558
        ]
      ],
      "group_id": null,
      "description": "",
      "shape_type": "polygon",
      "flags": {},
      "mask": null
    }
  ],
  "imagePath": "184-3.png",
  "imageData": null,
  "imageHeight": 640,
  "imageWidth": 640
}