{
  "version": "6.1.3",
  "flags": {},
  "shapes": [
    {
      "label": "parking",
      "points": [
        [
          26.52173913043481,
          400.4347826086956
        ],
        [
          241.73913043478262,
          330.86956521739125
        ],
        [
          225.79710144927537,
          329.42028985507244
        ],
        [
          67.82608695652175,
          363.4782608695652
        ],
        [
          28.69565217391306,
          372.89855072463763
        ],
        [
          20.00000000000003,
          380.86956521739125
        ]
      ],
      "group_id": null,
      "description": "",
      "shape_type": "polygon",
      "flags": {},
      "mask": null
    },
    {
      "label": "roadway",
      "points": [
        [
          330.8695652173913,
          312.0289855072464
        ],
        [
          306.23188405797106,
          308.40579710144925
        ],
        [
          238.84057971014494,
          335.9420289855072
        ],
        [
          0.0,
          411.4789593155229
        ],
        [
          2.6086956521739353,
          635.2173913043479
        ],
        [
          635.2173913043478,
          637.3913043478261
        ],
        [
          638.840579710145,
          545.3623188405797
        ],
        [
          396.81159420289856,
          366.3768115942029
        ]
      ],
      "group_id": null,
      "description": "",
      "shape_type": "polygon",
      "flags": {},
      "mask": null
    },
    {
      "label": "sidewalk",
      "points": [
        [
          0.4347826086956843,
          408.40579710144925
        ],
        [
          24.34782608695656,
          401.88405797101444
        ],
        [
          19.275362318840592,
          378.695652173913
        ],
        [
          30.86956521739131,
          367.1014492753623
        ],
        [
          227.97101449275362,
          327.2463768115942
        ],
        [
          245.3623188405797,
          329.42028985507244
        ],
        [
          300.4347826086957,
          308.40579710144925
        ],
        [
          267.82608695652175,
          312.0289855072464
        ],
        [
          191.0144927536232,
          325.07246376811594
        ],
        [
          39.56521739130437,
          336.66666666666663
        ],
        [
          0.4347826086956843,
          343.9130434782608
        ]
      ],
      "group_id": null,
      "description": "",
      "shape_type": "polygon",
      "flags": {},
      "mask": null
    },
    {
      "label": "sidewalk",
      "points": [
        [
          339.5652173913043,
          310.5797101449275
        ],
        [
          375.7971014492753,
          306.95652173913044
        ],
        [
          460.57971014492756,
          312.75362318840575
        ],
        [
          575.7971014492753,
          317.8260869565217
        ],
        [
          638.840579710145,
          321.4492753623188
        ],
        [
          638.840579710145,
          543.1884057971015
        ],
        [
          382.3188405797102,
          349.7101449275362
        ]
      ],
      "group_id": null,
      "description": "",
      "shape_type": "polygon",
      "flags": {},
      "mask": null
    }
  ],
  "imagePath": "25-3.png",
  "imageData": null,
  "imageHeight": 640,
  "imageWidth": 640
}